Workbook

Sheet 00_README
A1: PROJECT
A2: Capital Planning & Liquidity Management Model
A4: BUSINESS PROBLEM
A5: Leadership needs a consolidated view of liquidity, investment income, capital allocation, deposit maturities, FX exposure, and forward-looking scenarios.
A7: SOLUTION
A8: A dynamic Excel-based decision-support model integrating cash flow, term deposits, FX allocation, scenario planning, automated controls, and an executive dashboard.
A10: MODEL ARCHITECTURE
A11: Inputs -> Deposits -> Cash Flow -> FX Allocation -> Scenarios -> Controls -> Executive Dashboard
A13: KEY FEATURES
A14: 12-month capital forecast; Base / Optimistic / Stress scenarios; liquidity reserve management; term deposit maturity tracking; FX exposure monitoring; automated reconciliation controls; executive KPI dashboard; management insights.
A16: DECISION LOGIC
A17: Starting Capital -> Investment Income -> Operating Expenses -> Minimum Reserve -> Excess Liquidity -> Capital Allocation -> Reinvestment -> 12M Forecast
... A23: Financial Modeling; FP&A; Business Operations; Cash Flow Forecasting; Liquidity Management; Scenario Planning; Risk Controls; Management Reporting; Executive Dashboard Design; Decision Support

Sheet 01_DASHBOARD
A1: Capital Planning & Liquidity Management
A2: Cash Flow · Liquidity · Scenario Planning · FX Risk
A3: Synthetic Portfolio Model
A5: TOTAL CAPITAL | D5: AVAILABLE LIQUIDITY | G5: TERM DEPOSITS | J5: FX ASSETS | M5: NEXT MATURITY
A6: ='02_INPUTS'!$B$8 | D6: ='02_INPUTS'!$B$5 | G6: ='02_INPUTS'!$B$6 | J6: ='02_INPUTS'!$B$7 | M6: =MIN('03_DEPOSITS'!E5:E8)
A7: Cash + Deposits + FX | D7: Unrestricted USD Cash | G7: Active Principal | J7: USD Equivalent | M7: Future Active Deposit
A8: MONTHLY CASH BURN | D8: INVESTMENT INCOME | G8: LIQUIDITY COVERAGE | J8: FX EXPOSURE | M8: 12M FORECAST
A9: ='02_INPUTS'!$B$10+'02_INPUTS'!$B$11 | D9: ='04_CASH_FLOW'!C5 | G9: =D6/A9 | J9: =J6/A6 | M9: ='08_ANALYTICS'!C16
A10: USD / Month | D10: Current Month | G10: Liquidity Runway | J10: FX Assets / Total | M10: Base Month 12
A12: LIQUIDITY RUNWAY | D12: INCOME COVERAGE | G12: NEXT MATURITY | J12: STRESS DOWNSIDE | M12: EXCESS LIQUIDITY
A14: =G9 | D14: =D9/A9 | G14: =M6 | J14: =('08_ANALYTICS'!E16-'08_ANALYTICS'!C16)/'08_ANALYTICS'!C16 | M14: ='04_CASH_FLOW'!J5
A17: Opening Cash | B17: → | C17: Income | D17: → | E17: Expenses | F17: → | G17: Pre-Allocation Cash | H17: → | I17: Reserve | J17: → | K17: Excess Liquidity | L17: → | M17: Allocation | N17: → | O17: Closing Cash
I31: Cash | J31: ='08_ANALYTICS'!C21 | K31: Deposits | L31: ='08_ANALYTICS'!C22 | M31: FX | N31: ='08_ANALYTICS'!C23

Sheet 02_INPUTS
A1: Inputs
A2: — .
A4: Assumption | B4: Value | C4: Unit | D4: Role
A5: Current Available Liquidity | B5: 1350000 | C5: USD | D5: Input
A6: Active Term Deposit Principal | B6: 3800000 | C6: USD | D6: Check
A7: Current FX Assets USD | B7: 1450000 | C7: USD | D7: Input
A8: Current Total Capital | B8: =SUM(B5:B7) | C8: USD | D8: Formula
A9: Minimum Reserve | B9: 850000 | C9: USD | D9: Input
A10: Monthly Operating Expenses | B10: 145000 | C10: USD/month | D10: Input
A11: Other Operating Expenses | B11: 18000 | C11: USD/month | D11: Input
A12: Other Income | B12: 20000 | C12: USD/month | D12: Input
A13: Monthly FX Allocation Target | B13: 35000 | C13: USD/month | D13: Input
A14: Tax/Fee Rate | B14: 0.075 | C14: % | D14: Input
A15: Opening USD/FCU Rate | B15: 1.2 | C15: USD/FCU | D15: Input
A16: Opening FCU Units | B16: =B7/B15 | C16: FCU units | D16: Formula
A17: Day-Count Basis | B17: 365 | C17: days | D17: Input

Sheet 03_DEPOSITS
A1: Term Deposits
A2: — .
A4: Deposit ID | B4: Institution | C4: Principal | D4: Start Date | E4: Maturity Date | F4: Term Days | G4: Gross Rate % | H4: Tax/Fee % | I4: Net Rate % | J4: Gross Interest | K4: Net Interest | L4: Ending Balance | M4: Status
A5: TD-001 | B5: Institution A | C5: 950000 | D5: 46266 | E5: 46386 | F5: =E5-D5 | G5: 0.045 | H5: ='02_INPUTS'!$B$14 | I5: =G5*(1-H5) | J5: =C5*G5*F5/'02_INPUTS'!$B$17 | K5: =J5*(1-H5) | L5: =C5+K5 | M5: =IF(E5>=DATE(2026,9,1),"ACTIVE","MATURED")
A6: TD-002 | B6: Institution B | C6: 875000 | D6: 46296 | E6: 46446 | F6: =E6-D6 | G6: 0.048 | H6: ='02_INPUTS'!$B$14 | I6: =G6*(1-H6) | J6: =C6*G6*F6/'02_INPUTS'!$B$17 | K6: =J6*(1-H6) | L6: =C6+K6 | M6: =IF(E6>=DATE(2026,9,1),"ACTIVE","MATURED")
A7: TD-003 | B7: Institution C | C7: 1025000 | D7: 46327 | E7: 46538 | F7: =E7-D7 | G7: 0.05 | H7: ='02_INPUTS'!$B$14 | I7: =G7*(1-H7) | J7: =C7*G7*F7/'02_INPUTS'!$B$17 | K7: =J7*(1-H7) | L7: =C7+K7 | M7: =IF(E7>=DATE(2026,9,1),"ACTIVE","MATURED")
A8: TD-004 | B8: Treasury Counterparty 1 | C8: 950000 | D8: 46357 | E8: 46630 | F8: =E8-D8 | G8: 0.052 | H8: ='02_INPUTS'!$B$14 | I8: =G8*(1-H8) | J8: =C8*G8*F8/'02_INPUTS'!$B$17 | K8: =J8*(1-H8) | L8: =C8+K8 | M8: =IF(E8>=DATE(2026,9,1),"ACTIVE","MATURED")

Sheet 04_CASH_FLOW
A1: Base Cash Flow
A2: — .
A4: Month | B4: Opening Cash | C4: Investment Income | D4: Other Income | E4: Operating Expenses | F4: Other OpEx | G4: Maturity Principal | H4: Pre-Allocation Cash | I4: Minimum Reserve | J4: Excess Liquidity | K4: Actual Allocation | L4: Closing Cash | M4: Cash Flow Rec. | N4: Term Deposits | O4: FX Assets USD | P4: Total Capital
A5: 46266 | B5: ='02_INPUTS'!$B$5 | C5: =SUMPRODUCT(--('03_DEPOSITS'!$D$5:$D$8<=A5),--('03_DEPOSITS'!$E$5:$E$8>=A5),'03_DEPOSITS'!$C$5:$C$8,'03_DEPOSITS'!$I$5:$I$8)/12*'06_SCENARIOS'!$B$5 | D5: ='02_INPUTS'!$B$12 | E5: ='02_INPUTS'!$B$10*(1+'06_SCENARIOS'!$C$5)^0 | F5: ='02_INPUTS'!$B$11*(1+'06_SCENARIOS'!$C$5)^0 | G5: =SUMIFS('03_DEPOSITS'!$C$5:$C$8,'03_DEPOSITS'!$E$5:$E$8,A5) | H5: =B5+C5+D5-E5-F5+G5 | I5: ='02_INPUTS'!$B$9*'06_SCENARIOS'!$E$5 | J5: =MAX(0,H5-I5) | K5: ='05_FX_ALLOCATION'!H5 | L5: =H5-K5 | M5: =B5+C5+D5-E5-F5+G5-K5-L5 | N5: ='02_INPUTS'!$B$6-SUM($G$5:G5) | O5: ='05_FX_ALLOCATION'!M5 | P5: =L5+N5+O5
A6: 46296 | B6: =L5 | C6: =SUMPRODUCT(--('03_DEPOSITS'!$D$5:$D$8<=A6),--('03_DEPOSITS'!$E$5:$E$8>=A6),'03_DEPOSITS'!$C$5:$C$8,'03_DEPOSITS'!$I$5:$I$8)/12*'06_SCENARIOS'!$B$5 | D6: ='02_INPUTS'!$B$12 | E6: ='02_INPUTS'!$B$10*(1+'06_SCENARIOS'!$C$5)^1 | F6: ='02_INPUTS'!$B$11*(1+'06_SCENARIOS'!$C$5)^1 | G6: =SUMIFS('03_DEPOSITS'!$C$5:$C$8,'03_DEPOSITS'!$E$5:$E$8,A6) | H6: =B6+C6+D6-E6-F6+G6 | I6: ='02_INPUTS'!$B$9*'06_SCENARIOS'!$E$5 | J6: =MAX(0,H6-I6) | K6: ='05_FX_ALLOCATION'!H6 | L6: =H6-K6 | M6: =B6+C6+D6-E6-F6+G6-K6-L6 | N6: ='02_INPUTS'!$B$6-SUM($G$5:G6) | O6: ='05_FX_ALLOCATION'!M6 | P6: =L6+N6+O6
A7: 46327 | B7: =L6 | C7: =SUMPRODUCT(--('03_DEPOSITS'!$D$5:$D$8<=A7),--('03_DEPOSITS'!$E$5:$E$8>=A7),'03_DEPOSITS'!$C$5:$C$8,'03_DEPOSITS'!$I$5:$I$8)/12*'06_SCENARIOS'!$B$5 | D7: ='02_INPUTS'!$B$12 | E7: ='02_INPUTS'!$B$10*(1+'06_SCENARIOS'!$C$5)^2 | F7: ='02_INPUTS'!$B$11*(1+'06_SCENARIOS'!$C$5)^2 | G7: =SUMIFS('03_DEPOSITS'!$C$5:$C$8,'03_DEPOSITS'!$E$5:$E$8,A7) | H7: =B7+C7+D7-E7-F7+G7 | I7: ='02_INPUTS'!$B$9*'06_SCENARIOS'!$E$5 | J7: =MAX(0,H7-I7) | K7: ='05_FX_ALLOCATION'!H7 | L7: =H7-K7 | M7: =B7+C7+D7-E7-F7+G7-K7-L7 | N7: ='02_INPUTS'!$B$6-SUM($G$5:G7) | O7: ='05_FX_ALLOCATION'!M7 | P7: =L7+N7+O7
A8: 46357 | B8: =L7 | C8: =SUMPRODUCT(--('03_DEPOSITS'!$D$5:$D$8<=A8),--('03_DEPOSITS'!$E$5:$E$8>=A8),'03_DEPOSITS'!$C$5:$C$8,'03_DEPOSITS'!$I$5:$I$8)/12*'06_SCENARIOS'!$B$5 | D8: ='02_INPUTS'!$B$12 | E8: ='02_INPUTS'!$B$10*(1+'06_SCENARIOS'!$C$5)^3 | F8: ='02_INPUTS'!$B$11*(1+'06_SCENARIOS'!$C$5)^3 | G8: =SUMIFS('03_DEPOSITS'!$C$5:$C$8,'03_DEPOSITS'!$E$5:$E$8,A8) | H8: =B8+C8+D8-E8-F8+G8 | I8: ='02_INPUTS'!$B$9*'06_SCENARIOS'!$E$5 | J8: =MAX(0,H8-I8) | K8: ='05_FX_ALLOCATION'!H8 | L8: =H8-K8 | M8: =B8+C8+D8-E8-F8+G8-K8-L8 | N8: ='02_INPUTS'!$B$6-SUM($G$5:G8) | O8: ='05_FX_ALLOCATION'!M8 | P8: =L8+N8+O8
A9: 46388 | B9: =L8 | C9: =SUMPRODUCT(--('03_DEPOSITS'!$D$5:$D$8<=A9),--('03_DEPOSITS'!$E$5:$E$8>=A9),'03_DEPOSITS'!$C$5:$C$8,'03_DEPOSITS'!$I$5:$I$8)/12*'06_SCENARIOS'!$B$5 | D9: ='02_INPUTS'!$B$12 | E9: ='02_INPUTS'!$B$10*(1+'06_SCENARIOS'!$C$5)^4 | F9: ='02_INPUTS'!$B$11*(1+'06_SCENARIOS'!$C$5)^4 | G9: =SUMIFS('03_DEPOSITS'!$C$5:$C$8,'03_DEPOSITS'!$E$5:$E$8,A9) | H9: =B9+C9+D9-E9-F9+G9 | I9: ='02_INPUTS'!$B$9*'06_SCENARIOS'!$E$5 | J9: =MAX(0,H9-I9) | K9: ='05_FX_ALLOCATION'!H9 | L9: =H9-K9 | M9: =B9+C9+D9-E9-F9+G9-K9-L9 | N9: ='02_INPUTS'!$B$6-SUM($G$5:G9) | O9: ='05_FX_ALLOCATION'!M9 | P9: =L9+N9+O9
A10: 46419 | B10: =L9 | C10: =SUMPRODUCT(--('03_DEPOSITS'!$D$5:$D$8<=A10),--('03_DEPOSITS'!$E$5:$E$8>=A10),'03_DEPOSITS'!$C$5:$C$8,'03_DEPOSITS'!$I$5:$I$8)/12*'06_SCENARIOS'!$B$5 | D10: ='02_INPUTS'!$B$12 | E10: ='02_INPUTS'!$B$10*(1+'06_SCENARIOS'!$C$5)^5 | F10: ='02_INPUTS'!$B$11*(1+'06_SCENARIOS'!$C$5)^5 | G10: =SUMIFS('03_DEPOSITS'!$C$5:$C$8,'03_DEPOSITS'!$E$5:$E$8,A10) | H10: =B10+C10+D10-E10-F10+G10 | I10: ='02_INPUTS'!$B$9*'06_SCENARIOS'!$E$5 | J10: =MAX(0,H10-I10) | K10: ='05_FX_ALLOCATION'!H10 | L10: =H10-K10 | M10: =B10+C10+D10-E10-F10+G10-K10-L10 | N10: ='02_INPUTS'!$B$6-SUM($G$5:G10) | O10: ='05_FX_ALLOCATION'!M10 | P10: =L10+N10+O10
A11: 46447 | B11: =L10 | C11: =SUMPRODUCT(--('03_DEPOSITS'!$D$5:$D$8<=A11),--('03_DEPOSITS'!$E$5:$E$8>=A11),'03_DEPOSITS'!$C$5:$C$8,'03_DEPOSITS'!$I$5:$I$8)/12*'06_SCENARIOS'!$B$5 | D11: ='02_INPUTS'!$B$12 | E11: ='02_INPUTS'!$B$10*(1+'06_SCENARIOS'!$C$5)^6 | F11: ='02_INPUTS'!$B$11*(1+'06_SCENARIOS'!$C$5)^6 | G11: =SUMIFS('03_DEPOSITS'!$C$5:$C$8,'03_DEPOSITS'!$E$5:$E$8,A11) | H11: =B11+C11+D11-E11-F11+G11 | I11: ='02_INPUTS'!$B$9*'06_SCENARIOS'!$E$5 | J11: =MAX(0,H11-I11) | K11: ='05_FX_ALLOCATION'!H11 | L11: =H11-K11 | M11: =B11+C11+D11-E11-F11+G11-K11-L11 | N11: ='02_INPUTS'!$B$6-SUM($G$5:G11) | O11: ='05_FX_ALLOCATION'!M11 | P11: =L11+N11+O11
A12: 46478 | B12: =L11 | C12: =SUMPRODUCT(--('03_DEPOSITS'!$D$5:$D$8<=A12),--('03_DEPOSITS'!$E$5:$E$8>=A12),'03_DEPOSITS'!$C$5:$C$8,'03_DEPOSITS'!$I$5:$I$8)/12*'06_SCENARIOS'!$B$5 | D12: ='02_INPUTS'!$B$12 | E12: ='02_INPUTS'!$B$10*(1+'06_SCENARIOS'!$C$5)^7 | F12: ='02_INPUTS'!$B$11*(1+'06_SCENARIOS'!$C$5)^7 | G12: =SUMIFS('03_DEPOSITS'!$C$5:$C$8,'03_DEPOSITS'!$E$5:$E$8,A12) | H12: =B12+C12+D12-E12-F12+G12 | I12: ='02_INPUTS'!$B$9*'06_SCENARIOS'!$E$5 | J12: =MAX(0,H12-I12) | K12: ='05_FX_ALLOCATION'!H12 | L12: =H12-K12 | M12: =B12+C12+D12-E12-F12+G12-K12-L12 | N12: ='02_INPUTS'!$B$6-SUM($G$5:G12) | O12: ='05_FX_ALLOCATION'!M12 | P12: =L12+N12+O12
A13: 46508 | B13: =L12 | C13: =SUMPRODUCT(--('03_DEPOSITS'!$D$5:$D$8<=A13),--('03_DEPOSITS'!$E$5:$E$8>=A13),'03_DEPOSITS'!$C$5:$C$8,'03_DEPOSITS'!$I$5:$I$8)/12*'06_SCENARIOS'!$B$5 | D13: ='02_INPUTS'!$B$12 | E13: ='02_INPUTS'!$B$10*(1+'06_SCENARIOS'!$C$5)^8 | F13: ='02_INPUTS'!$B$11*(1+'06_SCENARIOS'!$C$5)^8 | G13: =SUMIFS('03_DEPOSITS'!$C$5:$C$8,'03_DEPOSITS'!$E$5:$E$8,A13) | H13: =B13+C13+D13-E13-F13+G13 | I13: ='02_INPUTS'!$B$9*'06_SCENARIOS'!$E$5 | J13: =MAX(0,H13-I13) | K13: ='05_FX_ALLOCATION'!H13 | L13: =H13-K13 | M13: =B13+C13+D13-E13-F13+G13-K13-L13 | N13: ='02_INPUTS'!$B$6-SUM($G$5:G13) | O13: ='05_FX_ALLOCATION'!M13 | P13: =L13+N13+O13
A14: 46539 | B14: =L13 | C14: =SUMPRODUCT(--('03_DEPOSITS'!$D$5:$D$8<=A14),--('03_DEPOSITS'!$E$5:$E$8>=A14),'03_DEPOSITS'!$C$5:$C$8,'03_DEPOSITS'!$I$5:$I$8)/12*'06_SCENARIOS'!$B$5 | D14: ='02_INPUTS'!$B$12 | E14: ='02_INPUTS'!$B$10*(1+'06_SCENARIOS'!$C$5)^9 | F14: ='02_INPUTS'!$B$11*(1+'06_SCENARIOS'!$C$5)^9 | G14: =SUMIFS('03_DEPOSITS'!$C$5:$C$8,'03_DEPOSITS'!$E$5:$E$8,A14) | H14: =B14+C14+D14-E14-F14+G14 | I14: ='02_INPUTS'!$B$9*'06_SCENARIOS'!$E$5 | J14: =MAX(0,H14-I14) | K14: ='05_FX_ALLOCATION'!H14 | L14: =H14-K14 | M14: =B14+C14+D14-E14-F14+G14-K14-L14 | N14: ='02_INPUTS'!$B$6-SUM($G$5:G14) | O14: ='05_FX_ALLOCATION'!M14 | P14: =L14+N14+O14
A15: 46569 | B15: =L14 | C15: =SUMPRODUCT(--('03_DEPOSITS'!$D$5:$D$8<=A15),--('03_DEPOSITS'!$E$5:$E$8>=A15),'03_DEPOSITS'!$C$5:$C$8,'03_DEPOSITS'!$I$5:$I$8)/12*'06_SCENARIOS'!$B$5 | D15: ='02_INPUTS'!$B$12 | E15: ='02_INPUTS'!$B$10*(1+'06_SCENARIOS'!$C$5)^10 | F15: ='02_INPUTS'!$B$11*(1+'06_SCENARIOS'!$C$5)^10 | G15: =SUMIFS('03_DEPOSITS'!$C$5:$C$8,'03_DEPOSITS'!$E$5:$E$8,A15) | H15: =B15+C15+D15-E15-F15+G15 | I15: ='02_INPUTS'!$B$9*'06_SCENARIOS'!$E$5 | J15: =MAX(0,H15-I15) | K15: ='05_FX_ALLOCATION'!H15 | L15: =H15-K15 | M15: =B15+C15+D15-E15-F15+G15-K15-L15 | N15: ='02_INPUTS'!$B$6-SUM($G$5:G15) | O15: ='05_FX_ALLOCATION'!M15 | P15: =L15+N15+O15
A16: 46600 | B16: =L15 | C16: =SUMPRODUCT(--('03_DEPOSITS'!$D$5:$D$8<=A16),--('03_DEPOSITS'!$E$5:$E$8>=A16),'03_DEPOSITS'!$C$5:$C$8,'03_DEPOSITS'!$I$5:$I$8)/12*'06_SCENARIOS'!$B$5 | D16: ='02_INPUTS'!$B$12 | E16: ='02_INPUTS'!$B$10*(1+'06_SCENARIOS'!$C$5)^11 | F16: ='02_INPUTS'!$B$11*(1+'06_SCENARIOS'!$C$5)^11 | G16: =SUMIFS('03_DEPOSITS'!$C$5:$C$8,'03_DEPOSITS'!$E$5:$E$8,A16) | H16: =B16+C16+D16-E16-F16+G16 | I16: ='02_INPUTS'!$B$9*'06_SCENARIOS'!$E$5 | J16: =MAX(0,H16-I16) | K16: ='05_FX_ALLOCATION'!H16 | L16: =H16-K16 | M16: =B16+C16+D16-E16-F16+G16-K16-L16 | N16: ='02_INPUTS'!$B$6-SUM($G$5:G16) | O16: ='05_FX_ALLOCATION'!M16 | P16: =L16+N16+O16

Sheet 05_FX_ALLOCATION
A1: FX Allocation
A2: — .
A4: Month | B4: Pre-Allocation Cash | C4: Reserve | D4: Excess Liquidity | E4: Target Allocation | F4: Allocation Limit | G4: Mode | H4: USD Allocation | I4: USD/FCU Rate | J4: FCU Purchased | K4: Cumulative FCU Units | L4: USD Cost Basis | M4: FX Assets USD | N4: Unrealized Gain/Loss | O4: FX Exposure % | P4: USD Conversion Rec.
A5: ='04_CASH_FLOW'!A5 | B5: ='04_CASH_FLOW'!H5 | C5: ='04_CASH_FLOW'!I5 | D5: ='04_CASH_FLOW'!J5 | E5: ='02_INPUTS'!$B$13*'06_SCENARIOS'!$F$5 | F5: =MIN(D5,E5) | G5: AUTO | H5: =F5 | I5: ='02_INPUTS'!$B$15*(1+'06_SCENARIOS'!$D$5)^0 | J5: =H5/I5 | K5: ='02_INPUTS'!$B$16+SUM($J$5:J5) | L5: ='02_INPUTS'!$B$7+SUM($H$5:H5) | M5: =K5*I5 | N5: =M5-L5 | O5: =M5/'04_CASH_FLOW'!P5 | P5: =M5-K5*I5
A6: ='04_CASH_FLOW'!A6 | B6: ='04_CASH_FLOW'!H6 | C6: ='04_CASH_FLOW'!I6 | D6: ='04_CASH_FLOW'!J6 | E6: ='02_INPUTS'!$B$13*'06_SCENARIOS'!$F$5 | F6: =MIN(D6,E6) | G6: AUTO | H6: =F6 | I6: ='02_INPUTS'!$B$15*(1+'06_SCENARIOS'!$D$5)^1 | J6: =H6/I6 | K6: ='02_INPUTS'!$B$16+SUM($J$5:J6) | L6: ='02_INPUTS'!$B$7+SUM($H$5:H6) | M6: =K6*I6 | N6: =M6-L6 | O6: =M6/'04_CASH_FLOW'!P6 | P6: =M6-K6*I6
A7: ='04_CASH_FLOW'!A7 | B7: ='04_CASH_FLOW'!H7 | C7: ='04_CASH_FLOW'!I7 | D7: ='04_CASH_FLOW'!J7 | E7: ='02_INPUTS'!$B$13*'06_SCENARIOS'!$F$5 | F7: =MIN(D7,E7) | G7: AUTO | H7: =F7 | I7: ='02_INPUTS'!$B$15*(1+'06_SCENARIOS'!$D$5)^2 | J7: =H7/I7 | K7: ='02_INPUTS'!$B$16+SUM($J$5:J7) | L7: ='02_INPUTS'!$B$7+SUM($H$5:H7) | M7: =K7*I7 | N7: =M7-L7 | O7: =M7/'04_CASH_FLOW'!P7 | P7: =M7-K7*I7
A8: ='04_CASH_FLOW'!A8 | B8: ='04_CASH_FLOW'!H8 | C8: ='04_CASH_FLOW'!I8 | D8: ='04_CASH_FLOW'!J8 | E8: ='02_INPUTS'!$B$13*'06_SCENARIOS'!$F$5 | F8: =MIN(D8,E8) | G8: AUTO | H8: =F8 | I8: ='02_INPUTS'!$B$15*(1+'06_SCENARIOS'!$D$5)^3 | J8: =H8/I8 | K8: ='02_INPUTS'!$B$16+SUM($J$5:J8) | L8: ='02_INPUTS'!$B$7+SUM($H$5:H8) | M8: =K8*I8 | N8: =M8-L8 | O8: =M8/'04_CASH_FLOW'!P8 | P8: =M8-K8*I8
A9: ='04_CASH_FLOW'!A9 | B9: ='04_CASH_FLOW'!H9 | C9: ='04_CASH_FLOW'!I9 | D9: ='04_CASH_FLOW'!J9 | E9: ='02_INPUTS'!$B$13*'06_SCENARIOS'!$F$5 | F9: =MIN(D9,E9) | G9: AUTO | H9: =F9 | I9: ='02_INPUTS'!$B$15*(1+'06_SCENARIOS'!$D$5)^4 | J9: =H9/I9 | K9: ='02_INPUTS'!$B$16+SUM($J$5:J9) | L9: ='02_INPUTS'!$B$7+SUM($H$5:H9) | M9: =K9*I9 | N9: =M9-L9 | O9: =M9/'04_CASH_FLOW'!P9 | P9: =M9-K9*I9
A10: ='04_CASH_FLOW'!A10 | B10: ='04_CASH_FLOW'!H10 | C10: ='04_CASH_FLOW'!I10 | D10: ='04_CASH_FLOW'!J10 | E10: ='02_INPUTS'!$B$13*'06_SCENARIOS'!$F$5 | F10: =MIN(D10,E10) | G10: AUTO | H10: =F10 | I10: ='02_INPUTS'!$B$15*(1+'06_SCENARIOS'!$D$5)^5 | J10: =H10/I10 | K10: ='02_INPUTS'!$B$16+SUM($J$5:J10) | L10: ='02_INPUTS'!$B$7+SUM($H$5:H10) | M10: =K10*I10 | N10: =M10-L10 | O10: =M10/'04_CASH_FLOW'!P10 | P10: =M10-K10*I10
A11: ='04_CASH_FLOW'!A11 | B11: ='04_CASH_FLOW'!H11 | C11: ='04_CASH_FLOW'!I11 | D11: ='04_CASH_FLOW'!J11 | E11: ='02_INPUTS'!$B$13*'06_SCENARIOS'!$F$5 | F11: =MIN(D11,E11) | G11: AUTO | H11: =F11 | I11: ='02_INPUTS'!$B$15*(1+'06_SCENARIOS'!$D$5)^6 | J11: =H11/I11 | K11: ='02_INPUTS'!$B$16+SUM($J$5:J11) | L11: ='02_INPUTS'!$B$7+SUM($H$5:H11) | M11: =K11*I11 | N11: =M11-L11 | O11: =M11/'04_CASH_FLOW'!P11 | P11: =M11-K11*I11
A12: ='04_CASH_FLOW'!A12 | B12: ='04_CASH_FLOW'!H12 | C12: ='04_CASH_FLOW'!I12 | D12: ='04_CASH_FLOW'!J12 | E12: ='02_INPUTS'!$B$13*'06_SCENARIOS'!$F$5 | F12: =MIN(D12,E12) | G12: AUTO | H12: =F12 | I12: ='02_INPUTS'!$B$15*(1+'06_SCENARIOS'!$D$5)^7 | J12: =H12/I12 | K12: ='02_INPUTS'!$B$16+SUM($J$5:J12) | L12: ='02_INPUTS'!$B$7+SUM($H$5:H12) | M12: =K12*I12 | N12: =M12-L12 | O12: =M12/'04_CASH_FLOW'!P12 | P12: =M12-K12*I12
A13: ='04_CASH_FLOW'!A13 | B13: ='04_CASH_FLOW'!H13 | C13: ='04_CASH_FLOW'!I13 | D13: ='04_CASH_FLOW'!J13 | E13: ='02_INPUTS'!$B$13*'06_SCENARIOS'!$F$5 | F13: =MIN(D13,E13) | G13: AUTO | H13: =F13 | I13: ='02_INPUTS'!$B$15*(1+'06_SCENARIOS'!$D$5)^8 | J13: =H13/I13 | K13: ='02_INPUTS'!$B$16+SUM($J$5:J13) | L13: ='02_INPUTS'!$B$7+SUM($H$5:H13) | M13: =K13*I13 | N13: =M13-L13 | O13: =M13/'04_CASH_FLOW'!P13 | P13: =M13-K13*I13
A14: ='04_CASH_FLOW'!A14 | B14: ='04_CASH_FLOW'!H14 | C14: ='04_CASH_FLOW'!I14 | D14: ='04_CASH_FLOW'!J14 | E14: ='02_INPUTS'!$B$13*'06_SCENARIOS'!$F$5 | F14: =MIN(D14,E14) | G14: AUTO | H14: =F14 | I14: ='02_INPUTS'!$B$15*(1+'06_SCENARIOS'!$D$5)^9 | J14: =H14/I14 | K14: ='02_INPUTS'!$B$16+SUM($J$5:J14) | L14: ='02_INPUTS'!$B$7+SUM($H$5:H14) | M14: =K14*I14 | N14: =M14-L14 | O14: =M14/'04_CASH_FLOW'!P14 | P14: =M14-K14*I14
A15: ='04_CASH_FLOW'!A15 | B15: ='04_CASH_FLOW'!H15 | C15: ='04_CASH_FLOW'!I15 | D15: ='04_CASH_FLOW'!J15 | E15: ='02_INPUTS'!$B$13*'06_SCENARIOS'!$F$5 | F15: =MIN(D15,E15) | G15: AUTO | H15: =F15 | I15: ='02_INPUTS'!$B$15*(1+'06_SCENARIOS'!$D$5)^10 | J15: =H15/I15 | K15: ='02_INPUTS'!$B$16+SUM($J$5:J15) | L15: ='02_INPUTS'!$B$7+SUM($H$5:H15) | M15: =K15*I15 | N15: =M15-L15 | O15: =M15/'04_CASH_FLOW'!P15 | P15: =M15-K15*I15
A16: ='04_CASH_FLOW'!A16 | B16: ='04_CASH_FLOW'!H16 | C16: ='04_CASH_FLOW'!I16 | D16: ='04_CASH_FLOW'!J16 | E16: ='02_INPUTS'!$B$13*'06_SCENARIOS'!$F$5 | F16: =MIN(D16,E16) | G16: AUTO | H16: =F16 | I16: ='02_INPUTS'!$B$15*(1+'06_SCENARIOS'!$D$5)^11 | J16: =H16/I16 | K16: ='02_INPUTS'!$B$16+SUM($J$5:J16) | L16: ='02_INPUTS'!$B$7+SUM($H$5:H16) | M16: =K16*I16 | N16: =M16-L16 | O16: =M16/'04_CASH_FLOW'!P16 | P16: =M16-K16*I16

Sheet 06_SCENARIOS
A1: Scenario Assumptions
A2: — .
A4: Scenario | B4: Yield Adj. | C4: OpEx Growth | D4: FX Rate Trend | E4: Reserve Mult. | F4: Allocation Mult. | G4: Narrative
A5: BASE | B5: 1 | C5: 0.0025 | D5: 0.001 | E5: 1 | F5: 1 | G5: Synthetic scenario assumptions.
A6: OPTIMISTIC | B6: 1.18 | C6: -0.001 | D6: 0.01 | E6: 0.95 | F6: 1.1 | G6: Synthetic scenario assumptions.
A7: STRESS | B7: 0.68 | C7: 0.02 | D7: -0.02 | E7: 1.15 | F7: 0.45 | G7: Synthetic scenario assumptions.

Sheet 07_CONTROLS
A1: Automated QA Controls
A2: — .
A4: Control | B4: Actual | C4: Expected | D4: Difference | E4: Tolerance | F4: Status | G4: Notes
A5: Circular Reference Structural Check | B5: 0 | C5: 0 | D5: =B5-C5 | E5: 0 | F5: =IF(ABS(D5)<=E5,"OK","CRITICAL") | G5: External Python graph scan must pass.
A6: Formula Error Check | B6: 0 | C6: 0 | D6: =B6-C6 | E6: 0 | F6: =IF(B6=C6,"OK","CRITICAL") | G6: Required cells screened for formula errors.
A7: Total Capital Reconciliation | B7: ='02_INPUTS'!$B$8 | C7: =SUM('02_INPUTS'!B5:B7) | D7: =B7-C7 | E7: 0.01 | F7: =IF(ABS(D7)<=E7,"OK","CRITICAL") | G7: Current capital identity.
A8: Cash Flow Reconciliation | B8: =MAX(ABS('04_CASH_FLOW'!M5),ABS('04_CASH_FLOW'!M6),ABS('04_CASH_FLOW'!M7),ABS('04_CASH_FLOW'!M8),ABS('04_CASH_FLOW'!M9),ABS('04_CASH_FLOW'!M10),ABS('04_CASH_FLOW'!M11),ABS('04_CASH_FLOW'!M12),ABS('04_CASH_FLOW'!M13),ABS('04_CASH_FLOW'!M14),ABS('04_CASH_FLOW'!M15),ABS('04_CASH_FLOW'!M16)) | C8: 0 | D8: =B8-C8 | E8: 0.01 | F8: =IF(ABS(D8)<=E8,"OK","CRITICAL") | G8: Monthly cash roll-forward.
A9: Deposit Calculation Reconciliation | B9: =MAX(ABS('03_DEPOSITS'!L5-'03_DEPOSITS'!C5-'03_DEPOSITS'!K5),ABS('03_DEPOSITS'!L6-'03_DEPOSITS'!C6-'03_DEPOSITS'!K6),ABS('03_DEPOSITS'!L7-'03_DEPOSITS'!C7-'03_DEPOSITS'!K7),ABS('03_DEPOSITS'!L8-'03_DEPOSITS'!C8-'03_DEPOSITS'!K8)) | C9: 0 | D9: =B9-C9 | E9: 0.01 | F9: =IF(ABS(D9)<=E9,"OK","CRITICAL") | G9: Deposit ending balance equals principal plus net interest.
A10: FX USD Conversion Check | B10: =MAX(ABS('05_FX_ALLOCATION'!P5),ABS('05_FX_ALLOCATION'!P6),ABS('05_FX_ALLOCATION'!P7),ABS('05_FX_ALLOCATION'!P8),ABS('05_FX_ALLOCATION'!P9),ABS('05_FX_ALLOCATION'!P10),ABS('05_FX_ALLOCATION'!P11),ABS('05_FX_ALLOCATION'!P12),ABS('05_FX_ALLOCATION'!P13),ABS('05_FX_ALLOCATION'!P14),ABS('05_FX_ALLOCATION'!P15),ABS('05_FX_ALLOCATION'!P16)) | C10: 0 | D10: =B10-C10 | E10: 0.01 | F10: =IF(ABS(D10)<=E10,"OK","CRITICAL") | G10: FCU units times USD/FCU equals FX assets USD.
A11: FX Exposure Range Check | B11: =MAX('05_FX_ALLOCATION'!O5:O16) | C11: 0.5 | D11: =MAX(0,B11-C11) | E11: 0 | F11: =IF(AND(MIN('05_FX_ALLOCATION'!O5:O16)>=0,B11<=C11),"OK","CRITICAL") | G11: FX exposure must stay plausible.
A12: Allocation <= Excess Liquidity Check | B12: =MAX('05_FX_ALLOCATION'!H5-'05_FX_ALLOCATION'!D5,'05_FX_ALLOCATION'!H6-'05_FX_ALLOCATION'!D6,'05_FX_ALLOCATION'!H7-'05_FX_ALLOCATION'!D7,'05_FX_ALLOCATION'!H8-'05_FX_ALLOCATION'!D8,'05_FX_ALLOCATION'!H9-'05_FX_ALLOCATION'!D9,'05_FX_ALLOCATION'!H10-'05_FX_ALLOCATION'!D10,'05_FX_ALLOCATION'!H11-'05_FX_ALLOCATION'!D11,'05_FX_ALLOCATION'!H12-'05_FX_ALLOCATION'!D12,'05_FX_ALLOCATION'!H13-'05_FX_ALLOCATION'!D13,'05_FX_ALLOCATION'!H14-'05_FX_ALLOCATION'!D14,'05_FX_ALLOCATION'!H15-'05_FX_ALLOCATION'!D15,'05_FX_ALLOCATION'!H16-'05_FX_ALLOCATION'!D16) | C12: 0 | D12: =MAX(0,B12-C12) | E12: 0.01 | F12: =IF(D12<=E12,"OK","CRITICAL") | G12: Allocation cannot exceed excess liquidity.
A13: Allocation Percent Sum Check | B13: =SUM('08_ANALYTICS'!C21:C23) | C13: 1 | D13: =B13-C13 | E13: 0.001 | F13: =IF(ABS(D13)<=E13,"OK","CRITICAL") | G13: Current components sum to 100%.
A14: Scenario Series Completeness | B14: =COUNT('08_ANALYTICS'!C5:E16) | C14: 36 | D14: =B14-C14 | E14: 0 | F14: =IF(B14=C14,"OK","CRITICAL") | G14: Three scenarios over twelve months.
A15: Scenario Ordering Check | B15: ='08_ANALYTICS'!D16>'08_ANALYTICS'!C16 | C15: TRUE | D15: 0 | E15: 0 | F15: =IF(AND(B15=TRUE,'08_ANALYTICS'!C16>'08_ANALYTICS'!E16),"OK","CRITICAL") | G15: Optimistic > Base > Stress.
A16: Dashboard KPI Integrity | B16: =COUNT('01_DASHBOARD'!A6,'01_DASHBOARD'!D6,'01_DASHBOARD'!G6,'01_DASHBOARD'!J6,'01_DASHBOARD'!M6,'01_DASHBOARD'!A9,'01_DASHBOARD'!D9,'01_DASHBOARD'!G9,'01_DASHBOARD'!J9,'01_DASHBOARD'!M9) | C16: 10 | D16: =B16-C16 | E16: 0 | F16: =IF(B16=C16,"OK","CRITICAL") | G16: All KPI outputs numeric/date.
A17: Dashboard 12M Forecast Reconciliation | B17: ='01_DASHBOARD'!M9 | C17: ='08_ANALYTICS'!C16 | D17: =B17-C17 | E17: 0.01 | F17: =IF(ABS(D17)<=E17,"OK","CRITICAL") | G17: Dashboard forecast equals Base Month 12 total capital.
A18: Data Type Integrity | B18: 0 | C18: 0 | D18: =B18-C18 | E18: 0 | F18: =IF(B18=C18,"OK","CRITICAL") | G18: Python data-type audit must pass.
A19: Missing Required Inputs | B19: =COUNTBLANK('02_INPUTS'!B5:B17) | C19: 0 | D19: =B19-C19 | E19: 0 | F19: =IF(B19=C19,"OK","CRITICAL") | G19: Required input cells populated.
A20: External Link Check | B20: 0 | C20: 0 | D20: =B20-C20 | E20: 0 | F20: =IF(B20=C20,"OK","CRITICAL") | G20: Package scan must find no external links.
A21: Privacy Leakage Check | B21: 0 | C21: 0 | D21: =B21-C21 | E21: 0 | F21: =IF(B21=C21,"OK","CRITICAL") | G21: Privacy forensic audit must pass.
A22: Liquidity Coverage Denominator > 0 | B22: ='01_DASHBOARD'!A9 | C22: 0 | D22: =B22-C22 | E22: 0 | F22: =IF(B22>C22,"OK","CRITICAL") | G22: Monthly Cash Burn must be positive.
A23: FX Exposure Denominator > 0 | B23: ='01_DASHBOARD'!A6 | C23: 0 | D23: =B23-C23 | E23: 0 | F23: =IF(B23>C23,"OK","CRITICAL") | G23: Total Capital must be positive.
A24: Investment Income KPI Is Numeric | B24: =COUNT('01_DASHBOARD'!D9) | C24: 1 | D24: =B24-C24 | E24: 0 | F24: =IF(B24=C24,"OK","CRITICAL") | G24: Current-month investment income must be numeric.
A25: Next Maturity KPI Is Valid Date | B25: ='01_DASHBOARD'!M6 | C25: 1 | D25: =B25-C25 | E25: 0 | F25: =IF(B25>C25,"OK","CRITICAL") | G25: Next maturity must be a true Excel date greater than zero.
A26: Management Insight Source Integrity | B26: =COUNT('01_DASHBOARD'!A14,'01_DASHBOARD'!D14,'01_DASHBOARD'!G14,'01_DASHBOARD'!J14,'01_DASHBOARD'!M14) | C26: 5 | D26: =B26-C26 | E26: 0 | F26: =IF(B26=C26,"OK","CRITICAL") | G26: Insights must consume validated numeric/date outputs.
A27: Required Dashboard KPI Error Check | B27: =SUM(N(ISERROR('01_DASHBOARD'!A6)),N(ISERROR('01_DASHBOARD'!D6)),N(ISERROR('01_DASHBOARD'!G6)),N(ISERROR('01_DASHBOARD'!J6)),N(ISERROR('01_DASHBOARD'!M6)),N(ISERROR('01_DASHBOARD'!A9)),N(ISERROR('01_DASHBOARD'!D9)),N(ISERROR('01_DASHBOARD'!G9)),N(ISERROR('01_DASHBOARD'!J9)),N(ISERROR('01_DASHBOARD'!M9)),N(ISERROR('01_DASHBOARD'!A14)),N(ISERROR('01_DASHBOARD'!D14)),N(ISERROR('01_DASHBOARD'!G14)),N(ISERROR('01_DASHBOARD'!J14)),N(ISERROR('01_DASHBOARD'!M14))) | C27: 0 | D27: =B27-C27 | E27: 0 | F27: =IF(B27=C27,"OK","CRITICAL") | G27: Required KPIs and insights must not resolve to formula errors.
A30: Overall Model Status | B30: =IF(COUNTIF(F5:F27,"CRITICAL")>0,"CRITICAL",IF(COUNTIF(F5:F27,"WARNING")>0,"WARNING","OK"))

Sheet 08_ANALYTICS
A1: Validated Analytics
A2: — .
A4: Month # | B4: Month | C4: Base | D4: Optimistic | E4: Stress | F4: Base Cash | G4: Base FX Exposure %
A5: 1 | B5: 46266 | C5: 6460295.3 | D5: 6460888.5 | E5: 6459240.8 | F5: 1175295.3 | G5: 0.22986565
A6: 2 | B6: 46296 | C6: 6324905.6 | D6: 6340645.2 | E6: 6288108.1 | F6: 1003420.6 | G6: 0.24055458
A7: 3 | B7: 46327 | C7: 6193094.4 | D7: 6225760.2 | E7: 6116607.9 | F7: 850000 | G7: 0.24916372
A8: 4 | B8: 46357 | C8: 6064703.2 | D8: 6116070.4 | E8: 5944886.2 | F8: 1635065.7 | G8: 0.26046411
A9: 5 | B9: 46388 | C9: 5932642.7 | D9: 6003199.3 | E9: 5767718.4 | F9: 1466425.5 | G9: 0.27242786
A10: 6 | B10: 46419 | C10: 5800207.1 | D10: 5891040.5 | E10: 5587271.1 | F10: 2172373.7 | G10: 0.2849611
A11: 7 | B11: 46447 | C11: 5664158 | D11: 5775779.2 | E11: 5401267.2 | F11: 1999671.8 | G11: 0.29827667
A12: 8 | B12: 46478 | C12: 5527732 | D12: 5661241 | E12: 5211831.2 | F12: 1826556.3 | G12: 0.31227558
A13: 9 | B13: 46508 | C13: 5390927.9 | D13: 5547431.3 | E13: 5018885.1 | F13: 2678026.1 | G13: 0.32701269
A14: 10 | B14: 46539 | C14: 5249794.4 | D14: 5429694.1 | E14: 4819662.8 | F14: 2500129.6 | G14: 0.34280672
A15: 11 | B15: 46569 | C15: 5108280.8 | D15: 5312696.5 | E15: 4616769.8 | F15: 2321816.4 | G15: 0.35950734
A16: 12 | B16: 46600 | C16: 4966386.2 | D16: 5196444.2 | E16: 4410123.6 | F16: 3093085.3 | G16: 0.37719598
A20: Asset Class | B20: USD Value | C20: Allocation %
A21: Available Liquidity | B21: ='02_INPUTS'!$B$5 | C21: =B21/SUM($B$21:$B$23)
A22: Term Deposits | B22: ='02_INPUTS'!$B$6 | C22: =B22/SUM($B$21:$B$23)
A23: FX Assets | B23: ='02_INPUTS'!$B$7 | C23: =B23/SUM($B$21:$B$23)
A25: Metric | B25: Cash | C25: Deposits | D25: FX
A26: Allocation % | B26: ='08_ANALYTICS'!C21 | C26: ='08_ANALYTICS'!C22 | D26: ='08_ANALYTICS'!C23
A27: KPI | B27: Dashboard Cell | C27: Expected Value | D27: Unit | E27: Difference
A28: Total Capital | B28: 01_DASHBOARD!A6 | C28: 6600000 | D28: USD | E28: ='01_DASHBOARD'!A6-C28
A29: Available Liquidity | B29: 01_DASHBOARD!D6 | C29: 1350000 | D29: USD | E29: ='01_DASHBOARD'!D6-C29
A30: Term Deposits | B30: 01_DASHBOARD!G6 | C30: 3800000 | D30: USD | E30: ='01_DASHBOARD'!G6-C30
A31: FX Assets | B31: 01_DASHBOARD!J6 | C31: 1450000 | D31: USD | E31: ='01_DASHBOARD'!J6-C31
A32: Monthly Cash Burn | B32: 01_DASHBOARD!A9 | C32: 163000 | D32: USD | E32: ='01_DASHBOARD'!A9-C32
A33: Investment Income | B33: 01_DASHBOARD!D9 | C33: 3295.3125 | D33: USD | E33: ='01_DASHBOARD'!D9-C33
A34: Liquidity Coverage | B34: 01_DASHBOARD!G9 | C34: 8.2822086 | D34: months | E34: ='01_DASHBOARD'!G9-C34
A35: FX Exposure % | B35: 01_DASHBOARD!J9 | C35: 0.21969697 | D35: % | E35: ='01_DASHBOARD'!J9-C35
A36: Next Maturity | B36: 01_DASHBOARD!M6 | C36: 46386 | D36: date | E36: ='01_DASHBOARD'!M6-C36
A37: 12M Forecast Capital | B37: 01_DASHBOARD!M9 | C37: 4966386.2 | D37: USD | E37: ='01_DASHBOARD'!M9-C37
